pycorm/__init__.py
pycorm/exceptions.py
pycorm/pycorm.py
pycorm-0.2.13.dist-info/top_level.txt
pycorm-0.2.13.dist-info/METADATA
pycorm-0.2.13.dist-info/DESCRIPTION.rst
pycorm-0.2.13.dist-info/metadata.json
pycorm-0.2.13.dist-info/WHEEL
pycorm-0.2.13.dist-info/RECORD
