Metadata-Version: 2.0
Name: pycorm
Version: 0.2.13
Summary: a pico orm that uses jsonschema
Home-page: https://github.com/sloev/pycorm
Author: Johannes Valbjørn
Author-email: johannes.valbjorn@gmail.com
License: MIT
Keywords: pycorm
Platform: UNKNOWN
Classifier: Development Status :: 2 - Pre-Alpha
Classifier: Intended Audience :: Developers
Classifier: License :: OSI Approved :: ISC License (ISCL)
Classifier: Natural Language :: English
Classifier: Programming Language :: Python :: 2
Classifier: Programming Language :: Python :: 2.6
Classifier: Programming Language :: Python :: 2.7
Requires-Dist: jsonschema
